transfreq/TopoObj_mod.py
transfreq/__init__.py
transfreq/functions.py
transfreq/utils.py
transfreq/viz.py
transfreq/data/transfreq_sample_evoked.fif
transfreq/data/transfreq_sample_resting.fif
transfreq-1.1.dist-info/LICENSE
transfreq-1.1.dist-info/METADATA
transfreq-1.1.dist-info/WHEEL
transfreq-1.1.dist-info/top_level.txt
transfreq-1.1.dist-info/RECORD
